fdata.py
fdata-0.2.3.dist-info/METADATA
fdata-0.2.3.dist-info/WHEEL
fdata-0.2.3.dist-info/top_level.txt
fdata-0.2.3.dist-info/RECORD
