Metadata-Version: 2.1
Name: fdata
Version: 0.2.3
Summary: FDA data cleaning and dataset creation tool
Home-page: https://github.com/G-Sprouts/FDA_sae
Author: Garrett Wankel
Author-email: g.wankel.1@gmail.com
License: UNKNOWN
Platform: UNKNOWN
Classifier: Programming Language :: Python :: 3
Classifier: Programming Language :: Python :: 3.8
Classifier: License :: OSI Approved :: MIT License
Classifier: Intended Audience :: Healthcare Industry
Classifier: Intended Audience :: End Users/Desktop
Classifier: Natural Language :: English
Classifier: Operating System :: OS Independent
Classifier: Programming Language :: Python
Classifier: Topic :: Scientific/Engineering :: Bio-Informatics
